README.md
setup.cfg
setup.py
shipstation/__init__.py
shipstation/api.py
shipstation.egg-info/PKG-INFO
shipstation.egg-info/SOURCES.txt
shipstation.egg-info/dependency_links.txt
shipstation.egg-info/requires.txt
shipstation.egg-info/top_level.txt